BMYReplication/analyze_missing.py
BMYReplication/compute_markups.py
BMYReplication/create_data.py
BMYReplication/estimate_coefficients.py
BMYReplication/main.py
BMYReplication/markup_figures.py
BMYReplication/utils.py
PyMarkup/0.0 Download Compustat.py
PyMarkup/0.1 Download CPI.py
PyMarkup/0.2 PPI Data Preparation.py
PyMarkup/0.3 theta_estimation.py
PyMarkup/0.4 Create Main Datasets.py
PyMarkup/0.5 Prepare Data for Figures and Tables.py
PyMarkup/1. Generate Figure 1 - Aggregate Markup.py
PyMarkup/2. Generate Figure 2 - CAGR of PPI vs Markup.py
PyMarkup/3. Generate Summary Statistics.py
PyMarkup/4. Generate Table 1.py
PyMarkup/Create_Data.py
PyMarkup/Estimate_Coefficients.py
PyMarkup/PyMarkup.py
PyMarkup/__init__.py
PyMarkup/__main__.py
PyMarkup/_version.py
PyMarkup/cli.py
PyMarkup/macro_var_calculation.py
PyMarkup/path_plot_config.py
PyMarkup/run_all.py
PyMarkup/utils.py
PyMarkup/cli/__init__.py
PyMarkup/cli/main.py
PyMarkup/core/__init__.py
PyMarkup/core/data_preparation.py
PyMarkup/core/markup_calculation.py
PyMarkup/data/__init__.py
PyMarkup/data/loaders.py
PyMarkup/estimators/__init__.py
PyMarkup/estimators/acf.py
PyMarkup/estimators/base.py
PyMarkup/estimators/cost_share.py
PyMarkup/estimators/wooldridge_iv.py
PyMarkup/io/__init__.py
PyMarkup/io/schemas.py
PyMarkup/pipeline/__init__.py
PyMarkup/pipeline/config.py
PyMarkup/pipeline/markup_pipeline.py
PyMarkup/utils/__init__.py
pymarkup_estimator-0.2.1.dist-info/licenses/LICENSE
pymarkup_estimator-0.2.1.dist-info/METADATA
pymarkup_estimator-0.2.1.dist-info/WHEEL
pymarkup_estimator-0.2.1.dist-info/entry_points.txt
pymarkup_estimator-0.2.1.dist-info/top_level.txt
pymarkup_estimator-0.2.1.dist-info/RECORD
