Metadata-Version: 2.4
Name: PyMarkup-estimator
Version: 0.2.1
Summary: A Python toolkit for estimating firm-level markups using production function-based marginal cost recovery.
Author-email: "Yangyang (Claire) Meng" <ym3593@nyu.edu>
Maintainer-email: "Yangyang (Claire) Meng" <ym3593@nyu.edu>
License: MIT
Project-URL: homepage, https://github.com/immortalsRDJ/PyMarkup
Project-URL: repository, https://github.com/immortalsRDJ/PyMarkup
Project-URL: documentation, https://pymarkup-estimator.readthedocs.io
Project-URL: bugs, https://github.com/immortalsRDJ/PyMarkup/issues
Project-URL: changelog, https://github.com/immortalsRDJ/PyMarkup/blob/main/CHANGELOG.md
Classifier: Development Status :: 3 - Alpha
Classifier: Intended Audience :: Science/Research
Classifier: License :: OSI Approved :: MIT License
Classifier: Programming Language :: Python :: 3
Classifier: Programming Language :: Python :: 3.10
Classifier: Programming Language :: Python :: 3.11
Classifier: Programming Language :: Python :: 3.12
Classifier: Programming Language :: Python :: 3.13
Classifier: Topic :: Scientific/Engineering
Requires-Python: >=3.10
License-File: LICENSE
Requires-Dist: pandas>=2.0.0
Requires-Dist: numpy>=1.24.0
Requires-Dist: scipy>=1.10.0
Requires-Dist: statsmodels>=0.14.0
Requires-Dist: linearmodels>=5.0
Requires-Dist: pydantic>=2.0
Requires-Dist: typer>=0.9.0
Requires-Dist: rich>=13.0
Requires-Dist: pyyaml>=6.0
Requires-Dist: matplotlib>=3.7.0
Requires-Dist: seaborn>=0.12.0
Requires-Dist: openpyxl>=3.0.0
Provides-Extra: test
Requires-Dist: coverage[toml]>=7.0; extra == "test"
Requires-Dist: pytest>=7.0; extra == "test"
Requires-Dist: pytest-cov>=4.0; extra == "test"
Requires-Dist: hypothesis>=6.0; extra == "test"
Requires-Dist: ruff>=0.1.0; extra == "test"
Requires-Dist: ty>=0.2.0; extra == "test"
Requires-Dist: ipdb>=0.13; extra == "test"
Provides-Extra: dev
Requires-Dist: PyMarkup-estimator[test]; extra == "dev"
Requires-Dist: jupyter>=1.0; extra == "dev"
Requires-Dist: ipython>=8.0; extra == "dev"
Provides-Extra: wrds
Requires-Dist: wrds>=3.1.0; extra == "wrds"
Dynamic: license-file
